README.rst
setup.py
renormimg/__init__.py
renormimg/tool.py
renormimg.egg-info/PKG-INFO
renormimg.egg-info/SOURCES.txt
renormimg.egg-info/dependency_links.txt
renormimg.egg-info/entry_points.txt
renormimg.egg-info/requires.txt
renormimg.egg-info/top_level.txt